ai_error_cli/__init__.py
ai_error_cli/ai_client.py
ai_error_cli/cli.py
ai_error_cli/config.py
ai_error_cli/executor.py
backend/__init__.py
backend/main.py
backend/routes/__init__.py
backend/routes/error_explainer.py
backend/schemas/__init__.py
backend/schemas/error_schema.py
backend/services/__init__.py
backend/services/ai_service.py
ai_error_cli-0.1.1.dist-info/METADATA
ai_error_cli-0.1.1.dist-info/WHEEL
ai_error_cli-0.1.1.dist-info/entry_points.txt
ai_error_cli-0.1.1.dist-info/top_level.txt
ai_error_cli-0.1.1.dist-info/RECORD
