Metadata-Version: 2.4
Name: ai-error-cli
Version: 0.1.1
Summary: CLI tool to explain Python runtime errors using AI
Author: Paraj Bhatasana
Author-email: bhatasanaparaj@gmail.com
Classifier: Programming Language :: Python :: 3
Classifier: License :: OSI Approved :: MIT License
Classifier: Operating System :: OS Independent
Requires-Python: >=3.8
Requires-Dist: requests
Requires-Dist: pydantic
Requires-Dist: fastapi
Requires-Dist: pydantic
Dynamic: author
Dynamic: author-email
Dynamic: classifier
Dynamic: description
Dynamic: description-content-type
Dynamic: requires-dist
Dynamic: requires-python
Dynamic: summary
